campo_estatico_mdf/__init__.py
campo_estatico_mdf/laplace_solver.py
campo_estatico_mdf_maria-0.1.1.dist-info/licenses/LICENSE
tests/__init__.py
tests/test_laplace_solver.py
campo_estatico_mdf_maria-0.1.1.dist-info/METADATA
campo_estatico_mdf_maria-0.1.1.dist-info/WHEEL
campo_estatico_mdf_maria-0.1.1.dist-info/top_level.txt
campo_estatico_mdf_maria-0.1.1.dist-info/RECORD
